trayicons/__main__.py
trayicons/config.py
trayicons/main.py
trayicons/tray_icons.py
trayicons/watchdog.py
trayicons/win_tray.py
trayicons-2025.6.30.1.dist-info/METADATA
trayicons-2025.6.30.1.dist-info/WHEEL
trayicons-2025.6.30.1.dist-info/entry_points.txt
trayicons-2025.6.30.1.dist-info/licenses/LICENSE
trayicons-2025.6.30.1.dist-info/RECORD
