Metadata-Version: 2.4
Name: trayicons
Version: 2025.6.30.1
Summary: Preview your tray icons made easy
Project-URL: Repository, https://github.com/soda92/trayicons
License-File: LICENSE
Requires-Python: >=3.11
Requires-Dist: pillow>=11.2.1
Requires-Dist: pywin32>=310
Requires-Dist: sodatools>=2025.2.16.0
Requires-Dist: toml>=0.10.2
Requires-Dist: watchdog>=6.0.0
